[
  {
    "time": "2025-08-27T13:00:00+00:00",
    "open": 480.22,
    "high": 482.44,
    "low": 479.37,
    "close": 481.93,
    "volume": 503.0
  },
  {
    "time": "2025-08-27T14:00:00+00:00",
    "open": 482.13,
    "high": 483.82,
    "low": 481.67,
    "close": 482.24,
    "volume": 677.0
  },
  {
    "time": "2025-08-27T15:00:00+00:00",
    "open": 482.38,
    "high": 483.31,
    "low": 482.18,
    "close": 483.28,
    "volume": 428.0
  },
  {
    "time": "2025-08-27T16:00:00+00:00",
    "open": 483.29,
    "high": 483.71,
    "low": 482.51,
    "close": 483.06,
    "volume": 235.0
  },
  {
    "time": "2025-08-27T17:00:00+00:00",
    "open": 482.94,
    "high": 483.6,
    "low": 482.75,
    "close": 483.57,
    "volume": 152.0
  },
  {
    "time": "2025-08-27T18:00:00+00:00",
    "open": 483.41,
    "high": 483.67,
    "low": 482.83,
    "close": 483.43,
    "volume": 241.0
  },
  {
    "time": "2025-08-27T19:00:00+00:00",
    "open": 483.38,
    "high": 483.39,
    "low": 482.51,
    "close": 482.56,
    "volume": 935.0
  },
  {
    "time": "2025-08-27T20:00:00+00:00",
    "open": 482.71,
    "high": 482.71,
    "low": 481.98,
    "close": 482.68,
    "volume": 1825.0
  },
  {
    "time": "2025-08-27T21:00:00+00:00",
    "open": 482.68,
    "high": 482.68,
    "low": 482.68,
    "close": 482.68,
    "volume": 0.0
  },
  {
    "time": "2025-08-27T22:00:00+00:00",
    "open": 482.68,
    "high": 482.68,
    "low": 482.68,
    "close": 482.68,
    "volume": 0.0
  },
  {
    "time": "2025-08-27T23:00:00+00:00",
    "open": 482.68,
    "high": 482.68,
    "low": 482.68,
    "close": 482.68,
    "volume": 0.0
  },
  {
    "time": "2025-08-28T11:00:00+00:00",
    "open": 482.77,
    "high": 482.77,
    "low": 482.77,
    "close": 482.77,
    "volume": 1.0
  },
  {
    "time": "2025-08-28T12:00:00+00:00",
    "open": 482.77,
    "high": 482.77,
    "low": 482.77,
    "close": 482.77,
    "volume": 0.0
  },
  {
    "time": "2025-08-28T13:00:00+00:00",
    "open": 482.56,
    "high": 483.01,
    "low": 479.13,
    "close": 482.04,
    "volume": 570.0
  },
  {
    "time": "2025-08-28T14:00:00+00:00",
    "open": 481.71,
    "high": 481.71,
    "low": 479.49,
    "close": 480.46,
    "volume": 429.0
  },
  {
    "time": "2025-08-28T15:00:00+00:00",
    "open": 480.25,
    "high": 480.96,
    "low": 479.44,
    "close": 480.96,
    "volume": 229.0
  },
  {
    "time": "2025-08-28T16:00:00+00:00",
    "open": 480.7,
    "high": 481.58,
    "low": 480.41,
    "close": 481.35,
    "volume": 215.0
  },
  {
    "time": "2025-08-28T17:00:00+00:00",
    "open": 481.41,
    "high": 481.6,
    "low": 480.78,
    "close": 481.2,
    "volume": 228.0
  },
  {
    "time": "2025-08-28T18:00:00+00:00",
    "open": 481.13,
    "high": 481.66,
    "low": 480.31,
    "close": 480.85,
    "volume": 426.0
  },
  {
    "time": "2025-08-28T19:00:00+00:00",
    "open": 480.85,
    "high": 482.51,
    "low": 480.79,
    "close": 482.15,
    "volume": 671.0
  },
  {
    "time": "2025-08-28T20:00:00+00:00",
    "open": 482.15,
    "high": 482.15,
    "low": 482.15,
    "close": 482.15,
    "volume": 2358.0
  },
  {
    "time": "2025-08-28T21:00:00+00:00",
    "open": 482.15,
    "high": 482.15,
    "low": 482.15,
    "close": 482.15,
    "volume": 0.0
  },
  {
    "time": "2025-08-28T22:00:00+00:00",
    "open": 482.15,
    "high": 482.15,
    "low": 482.15,
    "close": 482.15,
    "volume": 0.0
  },
  {
    "time": "2025-08-28T23:00:00+00:00",
    "open": 482.15,
    "high": 482.15,
    "low": 482.15,
    "close": 482.15,
    "volume": 0.0
  },
  {
    "time": "2025-08-29T13:00:00+00:00",
    "open": 481.16,
    "high": 483.32,
    "low": 481.01,
    "close": 482.6,
    "volume": 1265.0
  },
  {
    "time": "2025-08-29T14:00:00+00:00",
    "open": 482.46,
    "high": 482.67,
    "low": 479.49,
    "close": 480.24,
    "volume": 1230.0
  },
  {
    "time": "2025-08-29T15:00:00+00:00",
    "open": 480.33,
    "high": 480.59,
    "low": 479.42,
    "close": 480.55,
    "volume": 772.0
  },
  {
    "time": "2025-08-29T16:00:00+00:00",
    "open": 480.55,
    "high": 480.62,
    "low": 479.26,
    "close": 479.48,
    "volume": 753.0
  },
  {
    "time": "2025-08-29T17:00:00+00:00",
    "open": 479.37,
    "high": 480.47,
    "low": 479.11,
    "close": 480.45,
    "volume": 461.0
  },
  {
    "time": "2025-08-29T18:00:00+00:00",
    "open": 480.35,
    "high": 480.37,
    "low": 479.6,
    "close": 479.81,
    "volume": 245.0
  },
  {
    "time": "2025-08-29T19:00:00+00:00",
    "open": 479.86,
    "high": 479.86,
    "low": 477.0,
    "close": 478.13,
    "volume": 2249.0
  },
  {
    "time": "2025-08-29T20:00:00+00:00",
    "open": 478.29,
    "high": 478.29,
    "low": 477.25,
    "close": 478.29,
    "volume": 6093.0
  },
  {
    "time": "2025-08-29T21:00:00+00:00",
    "open": 476.38,
    "high": 476.38,
    "low": 476.37,
    "close": 476.38,
    "volume": 3.0
  },
  {
    "time": "2025-08-29T22:00:00+00:00",
    "open": 476.38,
    "high": 476.38,
    "low": 476.38,
    "close": 476.38,
    "volume": 0.0
  },
  {
    "time": "2025-08-29T23:00:00+00:00",
    "open": 476.38,
    "high": 476.38,
    "low": 476.37,
    "close": 476.38,
    "volume": 0.0
  },
  {
    "time": "2025-09-02T08:00:00+00:00",
    "open": 475.9,
    "high": 476.0,
    "low": 475.9,
    "close": 476.0,
    "volume": 2.0
  },
  {
    "time": "2025-09-02T09:00:00+00:00",
    "open": 476.0,
    "high": 476.0,
    "low": 476.0,
    "close": 476.0,
    "volume": 0.0
  },
  {
    "time": "2025-09-02T10:00:00+00:00",
    "open": 476.0,
    "high": 476.0,
    "low": 476.0,
    "close": 476.0,
    "volume": 0.0
  },
  {
    "time": "2025-09-02T11:00:00+00:00",
    "open": 476.0,
    "high": 476.0,
    "low": 476.0,
    "close": 476.0,
    "volume": 0.0
  },
  {
    "time": "2025-09-02T12:00:00+00:00",
    "open": 475.01,
    "high": 475.01,
    "low": 475.01,
    "close": 475.01,
    "volume": 1.0
  },
  {
    "time": "2025-09-02T13:00:00+00:00",
    "open": 476.99,
    "high": 479.75,
    "low": 473.66,
    "close": 474.98,
    "volume": 1094.0
  },
  {
    "time": "2025-09-02T14:00:00+00:00",
    "open": 475.06,
    "high": 477.16,
    "low": 474.53,
    "close": 475.35,
    "volume": 665.0
  },
  {
    "time": "2025-09-02T15:00:00+00:00",
    "open": 475.35,
    "high": 475.42,
    "low": 474.53,
    "close": 474.53,
    "volume": 607.0
  },
  {
    "time": "2025-09-02T16:00:00+00:00",
    "open": 474.17,
    "high": 474.17,
    "low": 472.5,
    "close": 473.25,
    "volume": 326.0
  },
  {
    "time": "2025-09-02T17:00:00+00:00",
    "open": 473.5,
    "high": 475.48,
    "low": 473.4,
    "close": 474.99,
    "volume": 292.0
  },
  {
    "time": "2025-09-02T18:00:00+00:00",
    "open": 475.0,
    "high": 475.2,
    "low": 473.92,
    "close": 474.23,
    "volume": 355.0
  },
  {
    "time": "2025-09-02T19:00:00+00:00",
    "open": 474.36,
    "high": 474.7,
    "low": 473.78,
    "close": 473.95,
    "volume": 850.0
  },
  {
    "time": "2025-09-02T20:00:00+00:00",
    "open": 474.14,
    "high": 474.14,
    "low": 474.14,
    "close": 474.14,
    "volume": 3134.0
  },
  {
    "time": "2025-09-02T21:00:00+00:00",
    "open": 474.14,
    "high": 474.14,
    "low": 474.14,
    "close": 474.14,
    "volume": 0.0
  },
  {
    "time": "2025-09-02T22:00:00+00:00",
    "open": 474.14,
    "high": 474.14,
    "low": 474.14,
    "close": 474.14,
    "volume": 0.0
  },
  {
    "time": "2025-09-02T23:00:00+00:00",
    "open": 474.14,
    "high": 474.14,
    "low": 474.14,
    "close": 474.14,
    "volume": 0.0
  },
  {
    "time": "2025-09-03T09:00:00+00:00",
    "open": 472.93,
    "high": 472.99,
    "low": 472.93,
    "close": 472.99,
    "volume": 2.0
  },
  {
    "time": "2025-09-03T10:00:00+00:00",
    "open": 471.6,
    "high": 473.07,
    "low": 471.6,
    "close": 473.07,
    "volume": 3.0
  },
  {
    "time": "2025-09-03T11:00:00+00:00",
    "open": 473.11,
    "high": 473.13,
    "low": 473.09,
    "close": 473.09,
    "volume": 3.0
  },
  {
    "time": "2025-09-03T12:00:00+00:00",
    "open": 473.09,
    "high": 473.09,
    "low": 473.09,
    "close": 473.09,
    "volume": 0.0
  },
  {
    "time": "2025-09-03T13:00:00+00:00",
    "open": 471.81,
    "high": 473.49,
    "low": 470.0,
    "close": 471.91,
    "volume": 463.0
  },
  {
    "time": "2025-09-03T14:00:00+00:00",
    "open": 471.49,
    "high": 473.91,
    "low": 471.4,
    "close": 473.52,
    "volume": 464.0
  },
  {
    "time": "2025-09-03T15:00:00+00:00",
    "open": 473.6,
    "high": 474.23,
    "low": 473.21,
    "close": 473.38,
    "volume": 311.0
  },
  {
    "time": "2025-09-03T16:00:00+00:00",
    "open": 473.42,
    "high": 473.7,
    "low": 472.33,
    "close": 472.79,
    "volume": 234.0
  },
  {
    "time": "2025-09-03T17:00:00+00:00",
    "open": 472.83,
    "high": 473.5,
    "low": 472.09,
    "close": 472.24,
    "volume": 215.0
  },
  {
    "time": "2025-09-03T18:00:00+00:00",
    "open": 472.44,
    "high": 473.61,
    "low": 472.09,
    "close": 472.48,
    "volume": 236.0
  },
  {
    "time": "2025-09-03T19:00:00+00:00",
    "open": 472.31,
    "high": 472.44,
    "low": 471.21,
    "close": 471.64,
    "volume": 1282.0
  },
  {
    "time": "2025-09-03T20:00:00+00:00",
    "open": 471.78,
    "high": 471.78,
    "low": 471.64,
    "close": 471.78,
    "volume": 3689.0
  },
  {
    "time": "2025-09-03T21:00:00+00:00",
    "open": 471.78,
    "high": 471.78,
    "low": 471.78,
    "close": 471.78,
    "volume": 0.0
  },
  {
    "time": "2025-09-03T22:00:00+00:00",
    "open": 471.78,
    "high": 471.78,
    "low": 471.78,
    "close": 471.78,
    "volume": 0.0
  },
  {
    "time": "2025-09-03T23:00:00+00:00",
    "open": 471.78,
    "high": 471.78,
    "low": 471.78,
    "close": 471.78,
    "volume": 0.0
  },
  {
    "time": "2025-09-04T12:00:00+00:00",
    "open": 475.75,
    "high": 478.0,
    "low": 475.75,
    "close": 478.0,
    "volume": 7.0
  },
  {
    "time": "2025-09-04T13:00:00+00:00",
    "open": 470.58,
    "high": 472.58,
    "low": 468.61,
    "close": 470.68,
    "volume": 507.0
  },
  {
    "time": "2025-09-04T14:00:00+00:00",
    "open": 470.67,
    "high": 470.87,
    "low": 468.67,
    "close": 470.25,
    "volume": 424.0
  },
  {
    "time": "2025-09-04T15:00:00+00:00",
    "open": 470.23,
    "high": 471.11,
    "low": 470.0,
    "close": 470.69,
    "volume": 1161.0
  },
  {
    "time": "2025-09-04T16:00:00+00:00",
    "open": 470.65,
    "high": 472.19,
    "low": 470.64,
    "close": 472.15,
    "volume": 501.0
  },
  {
    "time": "2025-09-04T17:00:00+00:00",
    "open": 472.15,
    "high": 472.52,
    "low": 471.31,
    "close": 471.96,
    "volume": 167.0
  },
  {
    "time": "2025-09-04T18:00:00+00:00",
    "open": 471.99,
    "high": 472.27,
    "low": 471.66,
    "close": 471.99,
    "volume": 219.0
  },
  {
    "time": "2025-09-04T19:00:00+00:00",
    "open": 472.07,
    "high": 472.93,
    "low": 471.61,
    "close": 472.33,
    "volume": 758.0
  },
  {
    "time": "2025-09-04T20:00:00+00:00",
    "open": 472.32,
    "high": 472.39,
    "low": 472.32,
    "close": 472.39,
    "volume": 5868.0
  },
  {
    "time": "2025-09-04T21:00:00+00:00",
    "open": 472.39,
    "high": 472.39,
    "low": 472.39,
    "close": 472.39,
    "volume": 0.0
  },
  {
    "time": "2025-09-04T22:00:00+00:00",
    "open": 471.57,
    "high": 471.57,
    "low": 471.57,
    "close": 471.57,
    "volume": 1.0
  },
  {
    "time": "2025-09-04T23:00:00+00:00",
    "open": 471.57,
    "high": 471.57,
    "low": 471.57,
    "close": 471.57,
    "volume": 0.0
  },
  {
    "time": "2025-09-05T13:00:00+00:00",
    "open": 471.15,
    "high": 474.55,
    "low": 469.7,
    "close": 474.55,
    "volume": 1005.0
  },
  {
    "time": "2025-09-05T14:00:00+00:00",
    "open": 474.16,
    "high": 475.05,
    "low": 468.9,
    "close": 468.91,
    "volume": 642.0
  },
  {
    "time": "2025-09-05T15:00:00+00:00",
    "open": 468.91,
    "high": 469.93,
    "low": 467.26,
    "close": 467.65,
    "volume": 468.0
  },
  {
    "time": "2025-09-05T16:00:00+00:00",
    "open": 467.84,
    "high": 468.33,
    "low": 466.76,
    "close": 467.55,
    "volume": 203.0
  },
  {
    "time": "2025-09-05T17:00:00+00:00",
    "open": 467.55,
    "high": 467.84,
    "low": 466.59,
    "close": 466.87,
    "volume": 188.0
  },
  {
    "time": "2025-09-05T18:00:00+00:00",
    "open": 467.17,
    "high": 469.27,
    "low": 466.72,
    "close": 469.24,
    "volume": 285.0
  },
  {
    "time": "2025-09-05T19:00:00+00:00",
    "open": 469.29,
    "high": 469.73,
    "low": 468.75,
    "close": 469.41,
    "volume": 648.0
  },
  {
    "time": "2025-09-05T20:00:00+00:00",
    "open": 469.52,
    "high": 469.52,
    "low": 468.62,
    "close": 468.62,
    "volume": 2366.0
  },
  {
    "time": "2025-09-05T21:00:00+00:00",
    "open": 468.62,
    "high": 468.62,
    "low": 468.62,
    "close": 468.62,
    "volume": 0.0
  },
  {
    "time": "2025-09-05T22:00:00+00:00",
    "open": 468.62,
    "high": 468.62,
    "low": 468.62,
    "close": 468.62,
    "volume": 0.0
  },
  {
    "time": "2025-09-05T23:00:00+00:00",
    "open": 468.62,
    "high": 468.62,
    "low": 468.62,
    "close": 468.62,
    "volume": 0.0
  }
]